numan/__init__.py
numan/analysis.py
numan/notifications.py
numan/plots.py
numan/project.py
numan/report.py
numan/runner.py
numan/utils.py
numan/visualization.py
numan-1.1.1.dist-info/LICENSE.md
numan-1.1.1.dist-info/METADATA
numan-1.1.1.dist-info/WHEEL
numan-1.1.1.dist-info/top_level.txt
numan-1.1.1.dist-info/RECORD
