Metadata-Version: 2.1
Name: numan
Version: 1.1.1
Summary: numerosity analysis package
Author-email: Anna Nadtochiy <nadtochi@usc.edu>
Project-URL: Homepage, https://github.com/LemonJust/numan
Classifier: Development Status :: 3 - Alpha
Classifier: Intended Audience :: Science/Research
Classifier: Topic :: Scientific/Engineering :: Image Processing
Classifier: Programming Language :: Python :: 3
Classifier: License :: OSI Approved :: MIT License
Classifier: Operating System :: OS Independent
Requires-Python: >=3.10
License-File: LICENSE.md
Requires-Dist: vodex <2.0.0,>=1.0.19
Requires-Dist: pypdf2
Requires-Dist: reportlab
Requires-Dist: scipy
Requires-Dist: ipykernel
Requires-Dist: urllib3
Requires-Dist: nbconvert
Requires-Dist: matplotlib
Requires-Dist: pandas
Provides-Extra: dev
Requires-Dist: bumpver ; extra == 'dev'
